{
    "id": "dss-plugin-amazon-transcribe",
    "version": "0.1.0",
    "meta": {
        "label": "Amazon Transcribe",
        "category": "Natural Language Processing",
        "description": "Amazon Transcribe plugin. The plugin takes audio files from a folder connected to Amazon S3 and make its transcription through Amazon Transcribe.",
        "author": "Dataiku (Jeremy PLASSMANN)",
        "icon": "icon-font-awesome-3.2.1",
        "licenseInfo": "Apache Software License",
        "url": "https://www.dataiku.com/product/plugins/your-plugin-id/",
        "tags": [
            "myTag"
        ],
        "supportLevel": "NOT_SUPPORTED"
    }
}
